{
  "project_info": {
    "project_number": "970846969532",
    "firebase_url": "https://quick-scan-master.firebaseio.com",
    "project_id": "quick-scan-master",
    "storage_bucket": "quick-scan-master.appspot.com"
  },
  "client": [
    {
      "client_info": {
        "mobilesdk_app_id": "1:970846969532:android:f893a07f1c728b64",
        "android_client_info": {
          "package_name": "d.tonyandfriends.thirdtimesthecharm"
        }
      },
      "oauth_client": [
        {
          "client_id": "970846969532-ap0dp5o4a6vglma69ge124kj4qntrfrc.apps.googleusercontent.com",
          "client_type": 1,
          "android_info": {
            "package_name": "d.tonyandfriends.thirdtimesthecharm",
            "certificate_hash": "a4494257925689b5370688cc0e762c1d0387f2eb"
          }
        },
        {
          "client_id": "970846969532-lqb3jcf2g3e46madqhubqjh4a9umoa2e.apps.googleusercontent.com",
          "client_type": 3
        }
      ],
      "api_key": [
        {
          "current_key": "AIzaSyBp9C39zqkiKVXEUjbw9n0smDax3Bz0Rg4"
        }
      ],
      "services": {
        "analytics_service": {
          "status": 1
        },
        "appinvite_service": {
          "status": 2,
          "other_platform_oauth_client": [
            {
              "client_id": "970846969532-lqb3jcf2g3e46madqhubqjh4a9umoa2e.apps.googleusercontent.com",
              "client_type": 3
            }
          ]
        },
        "ads_service": {
          "status": 2
        }
      }
    }
  ],
  "configuration_version": "1"
}